[
  {
    "ref": "context-region_1781", 
    "capacity": 64, 
    "type": "context", 
    "name": "315 Rocky Rd", 
    "mods": [
      {
        "town_dir": "\u007f", 
        "neighbors": [
          "", 
          "context-region_1779", 
          "context-region_1782", 
          "context-region_1783"
        ], 
        "orientation": 3, 
        "nitty_bits": 3, 
        "port_dir": "~", 
        "type": "Region"
      }
    ]
  }, 
  {
    "ref": "item-Mailbox_object_12655", 
    "mods": [
      {
        "style": 0, 
        "orientation": 16, 
        "gr_state": 0, 
        "y": 155, 
        "x": 124, 
        "type": "Mailbox"
      }
    ], 
    "type": "item", 
    "name": "Mailbox", 
    "in": "context-region_1781"
  }, 
  {
    "ref": "item-Plant_object_12654", 
    "mods": [
      {
        "style": 1, 
        "orientation": 17, 
        "mass": 1, 
        "gr_state": 0, 
        "y": 33, 
        "x": 48, 
        "type": "Plant"
      }
    ], 
    "type": "item", 
    "name": "Plant", 
    "in": "context-region_1781"
  }, 
  {
    "ref": "item-Plant_object_12657", 
    "mods": [
      {
        "style": 1, 
        "orientation": 17, 
        "mass": 1, 
        "gr_state": 0, 
        "y": 33, 
        "x": 84, 
        "type": "Plant"
      }
    ], 
    "type": "item", 
    "name": "Plant", 
    "in": "context-region_1781"
  }, 
  {
    "ref": "item-Sign_object_12656", 
    "mods": [
      {
        "style": 5, 
        "orientation": 16, 
        "ascii": [
          32, 
          32, 
          32, 
          51, 
          49, 
          53, 
          32, 
          32, 
          32, 
          32, 
          32, 
          32, 
          32, 
          32, 
          32, 
          32, 
          32, 
          32, 
          32, 
          32, 
          32, 
          32, 
          32, 
          32, 
          32, 
          32, 
          32, 
          32, 
          32, 
          32, 
          32, 
          32, 
          32, 
          32, 
          32, 
          32, 
          32, 
          32, 
          32, 
          32
        ], 
        "gr_state": 8, 
        "y": 32, 
        "x": 132, 
        "type": "Sign"
      }
    ], 
    "type": "item", 
    "name": "Sign", 
    "in": "context-region_1781"
  }, 
  {
    "ref": "item-Wall_object_12651", 
    "mods": [
      {
        "style": 7, 
        "orientation": 172, 
        "gr_state": 0, 
        "y": 2, 
        "x": 0, 
        "type": "Wall"
      }
    ], 
    "type": "item", 
    "name": "Wall", 
    "in": "context-region_1781"
  }, 
  {
    "ref": "item-Wall_object_12650", 
    "mods": [
      {
        "style": 4, 
        "orientation": 0, 
        "gr_state": 0, 
        "y": 0, 
        "x": 0, 
        "type": "Wall"
      }
    ], 
    "type": "item", 
    "name": "Wall", 
    "in": "context-region_1781"
  }, 
  {
    "ref": "item-Plant_object_12653", 
    "mods": [
      {
        "style": 1, 
        "orientation": 16, 
        "mass": 1, 
        "gr_state": 0, 
        "y": 33, 
        "x": 60, 
        "type": "Plant"
      }
    ], 
    "type": "item", 
    "name": "Plant", 
    "in": "context-region_1781"
  }, 
  {
    "ref": "item-Building_object_12652", 
    "mods": [
      {
        "style": 0, 
        "orientation": 17, 
        "gr_state": 0, 
        "y": 32, 
        "x": 72, 
        "type": "Building"
      }
    ], 
    "type": "item", 
    "name": "Building", 
    "in": "context-region_1781"
  }, 
  {
    "ref": "item-Plant_object_12659", 
    "mods": [
      {
        "style": 1, 
        "orientation": 17, 
        "mass": 1, 
        "gr_state": 0, 
        "y": 33, 
        "x": 12, 
        "type": "Plant"
      }
    ], 
    "type": "item", 
    "name": "Plant", 
    "in": "context-region_1781"
  }, 
  {
    "ref": "item-Plant_object_12658", 
    "mods": [
      {
        "style": 1, 
        "orientation": 16, 
        "mass": 1, 
        "gr_state": 0, 
        "y": 33, 
        "x": 24, 
        "type": "Plant"
      }
    ], 
    "type": "item", 
    "name": "Plant", 
    "in": "context-region_1781"
  }, 
  {
    "ref": "item-Ground_object_12649", 
    "mods": [
      {
        "style": 1, 
        "orientation": 220, 
        "gr_state": 0, 
        "y": 4, 
        "x": 0, 
        "type": "Ground"
      }
    ], 
    "type": "item", 
    "name": "Ground", 
    "in": "context-region_1781"
  }, 
  {
    "ref": "item-Street_object_12660", 
    "mods": [
      {
        "style": 0, 
        "orientation": 104, 
        "gr_state": 6, 
        "y": 12, 
        "x": 68, 
        "type": "Street"
      }
    ], 
    "type": "item", 
    "name": "Street", 
    "in": "context-region_1781"
  }, 
  {
    "ref": "item-Street_object_12661", 
    "mods": [
      {
        "style": 0, 
        "orientation": 104, 
        "gr_state": 6, 
        "y": 12, 
        "x": 68, 
        "type": "Street"
      }
    ], 
    "type": "item", 
    "name": "Street", 
    "in": "context-region_1781"
  }
]