[
  {
    "ref": "context-region_1196", 
    "capacity": 64, 
    "type": "context", 
    "name": "45 This Way", 
    "mods": [
      {
        "town_dir": "\u007f", 
        "neighbors": [
          "context-region_1197", 
          "context-region_1198", 
          "", 
          "context-region_1194"
        ], 
        "orientation": 1, 
        "nitty_bits": 3, 
        "port_dir": "\u007f", 
        "type": "Region"
      }
    ]
  }, 
  {
    "ref": "item-Mailbox_object_3825", 
    "mods": [
      {
        "style": 0, 
        "orientation": 0, 
        "gr_state": 0, 
        "y": 158, 
        "x": 100, 
        "type": "Mailbox"
      }
    ], 
    "type": "item", 
    "name": "Mailbox", 
    "in": "context-region_1196"
  }, 
  {
    "ref": "item-Bush_object_3824", 
    "mods": [
      {
        "style": 3, 
        "orientation": 41, 
        "gr_state": 1, 
        "y": 34, 
        "x": 60, 
        "type": "Bush"
      }
    ], 
    "type": "item", 
    "name": "Bush", 
    "in": "context-region_1196"
  }, 
  {
    "ref": "item-Street_object_3827", 
    "mods": [
      {
        "style": 0, 
        "orientation": 0, 
        "gr_state": 6, 
        "y": 10, 
        "x": 68, 
        "type": "Street"
      }
    ], 
    "type": "item", 
    "name": "Street", 
    "in": "context-region_1196"
  }, 
  {
    "ref": "item-Sign_object_3826", 
    "mods": [
      {
        "style": 5, 
        "orientation": 0, 
        "ascii": [
          32, 
          32, 
          32, 
          52, 
          53, 
          32, 
          32, 
          32, 
          32, 
          32, 
          32, 
          32, 
          32, 
          32, 
          32, 
          32, 
          32, 
          32, 
          32, 
          32, 
          32, 
          32, 
          32, 
          32, 
          32, 
          32, 
          32, 
          32, 
          32, 
          32, 
          32, 
          32, 
          32, 
          32, 
          32, 
          32, 
          32, 
          32, 
          32, 
          32
        ], 
        "gr_state": 8, 
        "y": 32, 
        "x": 80, 
        "type": "Sign"
      }
    ], 
    "type": "item", 
    "name": "Sign", 
    "in": "context-region_1196"
  }, 
  {
    "ref": "item-Wall_object_3821", 
    "mods": [
      {
        "style": 7, 
        "orientation": 172, 
        "gr_state": 0, 
        "y": 2, 
        "x": 0, 
        "type": "Wall"
      }
    ], 
    "type": "item", 
    "name": "Wall", 
    "in": "context-region_1196"
  }, 
  {
    "ref": "item-Ground_object_3819", 
    "mods": [
      {
        "style": 1, 
        "orientation": 172, 
        "gr_state": 0, 
        "y": 4, 
        "x": 0, 
        "type": "Ground"
      }
    ], 
    "type": "item", 
    "name": "Ground", 
    "in": "context-region_1196"
  }, 
  {
    "ref": "item-Bush_object_3823", 
    "mods": [
      {
        "style": 3, 
        "orientation": 40, 
        "gr_state": 1, 
        "y": 35, 
        "x": 16, 
        "type": "Bush"
      }
    ], 
    "type": "item", 
    "name": "Bush", 
    "in": "context-region_1196"
  }, 
  {
    "ref": "item-Building_object_3822", 
    "mods": [
      {
        "style": 0, 
        "orientation": 112, 
        "gr_state": 3, 
        "y": 32, 
        "x": 32, 
        "type": "Building"
      }
    ], 
    "type": "item", 
    "name": "Building", 
    "in": "context-region_1196"
  }, 
  {
    "ref": "item-Wall_object_3820", 
    "mods": [
      {
        "style": 6, 
        "orientation": 132, 
        "gr_state": 0, 
        "y": 0, 
        "x": 0, 
        "type": "Wall"
      }
    ], 
    "type": "item", 
    "name": "Wall", 
    "in": "context-region_1196"
  }
]