[
  {
    "ref": "context-region_1032", 
    "capacity": 64, 
    "type": "context", 
    "name": "58 Bleem St", 
    "mods": [
      {
        "town_dir": "\u007f", 
        "neighbors": [
          "context-region_1030", 
          "context-region_1033", 
          "context-region_1034", 
          ""
        ], 
        "orientation": 2, 
        "nitty_bits": 3, 
        "port_dir": "\u007f", 
        "type": "Region"
      }
    ]
  }, 
  {
    "ref": "item-Ground_object_2317", 
    "mods": [
      {
        "style": 1, 
        "orientation": 252, 
        "gr_state": 0, 
        "y": 4, 
        "x": 0, 
        "type": "Ground"
      }
    ], 
    "type": "item", 
    "name": "Ground", 
    "in": "context-region_1032"
  }, 
  {
    "ref": "item-Wall_object_2318", 
    "mods": [
      {
        "style": 4, 
        "orientation": 0, 
        "gr_state": 0, 
        "y": 0, 
        "x": 0, 
        "type": "Wall"
      }
    ], 
    "type": "item", 
    "name": "Wall", 
    "in": "context-region_1032"
  }, 
  {
    "ref": "item-Wall_object_2319", 
    "mods": [
      {
        "style": 7, 
        "orientation": 172, 
        "gr_state": 0, 
        "y": 2, 
        "x": 0, 
        "type": "Wall"
      }
    ], 
    "type": "item", 
    "name": "Wall", 
    "in": "context-region_1032"
  }, 
  {
    "ref": "item-Street_object_2329", 
    "mods": [
      {
        "style": 0, 
        "orientation": 8, 
        "gr_state": 6, 
        "y": 7, 
        "x": 68, 
        "type": "Street"
      }
    ], 
    "type": "item", 
    "name": "Street", 
    "in": "context-region_1032"
  }, 
  {
    "ref": "item-Fence_object_2328", 
    "mods": [
      {
        "style": 0, 
        "orientation": 0, 
        "gr_state": 0, 
        "y": 33, 
        "x": 132, 
        "type": "Fence"
      }
    ], 
    "type": "item", 
    "name": "Fence", 
    "in": "context-region_1032"
  }, 
  {
    "ref": "item-Fence_object_2325", 
    "mods": [
      {
        "style": 0, 
        "orientation": 0, 
        "gr_state": 2, 
        "y": 33, 
        "x": 92, 
        "type": "Fence"
      }
    ], 
    "type": "item", 
    "name": "Fence", 
    "in": "context-region_1032"
  }, 
  {
    "ref": "item-Fence_object_2324", 
    "mods": [
      {
        "style": 0, 
        "orientation": 0, 
        "gr_state": 0, 
        "y": 33, 
        "x": 64, 
        "type": "Fence"
      }
    ], 
    "type": "item", 
    "name": "Fence", 
    "in": "context-region_1032"
  }, 
  {
    "ref": "item-Fence_object_2327", 
    "mods": [
      {
        "style": 0, 
        "orientation": 0, 
        "gr_state": 2, 
        "y": 161, 
        "x": 108, 
        "type": "Fence"
      }
    ], 
    "type": "item", 
    "name": "Fence", 
    "in": "context-region_1032"
  }, 
  {
    "ref": "item-Plant_object_2326", 
    "mods": [
      {
        "style": 2, 
        "orientation": 32, 
        "mass": 1, 
        "gr_state": 0, 
        "y": 39, 
        "x": 76, 
        "type": "Plant"
      }
    ], 
    "type": "item", 
    "name": "Plant", 
    "in": "context-region_1032"
  }, 
  {
    "ref": "item-Bush_object_2321", 
    "mods": [
      {
        "style": 0, 
        "orientation": 172, 
        "gr_state": 0, 
        "y": 57, 
        "x": 108, 
        "type": "Bush"
      }
    ], 
    "type": "item", 
    "name": "Bush", 
    "in": "context-region_1032"
  }, 
  {
    "ref": "item-Building_object_2320", 
    "mods": [
      {
        "style": 0, 
        "orientation": 172, 
        "gr_state": 0, 
        "y": 32, 
        "x": 32, 
        "type": "Building"
      }
    ], 
    "type": "item", 
    "name": "Building", 
    "in": "context-region_1032"
  }, 
  {
    "ref": "item-Mailbox_object_2323", 
    "mods": [
      {
        "style": 0, 
        "orientation": 97, 
        "gr_state": 0, 
        "y": 151, 
        "x": 20, 
        "type": "Mailbox"
      }
    ], 
    "type": "item", 
    "name": "Mailbox", 
    "in": "context-region_1032"
  }, 
  {
    "ref": "item-Sign_object_2322", 
    "mods": [
      {
        "style": 5, 
        "orientation": 16, 
        "ascii": [
          32, 
          32, 
          32, 
          53, 
          56, 
          32, 
          32, 
          32, 
          32, 
          32, 
          32, 
          32, 
          32, 
          32, 
          32, 
          32, 
          32, 
          32, 
          32, 
          32, 
          32, 
          32, 
          32, 
          32, 
          32, 
          32, 
          32, 
          32, 
          32, 
          32, 
          32, 
          32, 
          32, 
          32, 
          32, 
          32, 
          32, 
          32, 
          32, 
          32
        ], 
        "gr_state": 8, 
        "y": 57, 
        "x": 72, 
        "type": "Sign"
      }
    ], 
    "type": "item", 
    "name": "Sign", 
    "in": "context-region_1032"
  }
]