[
  {
    "ref": "context-region_1068", 
    "capacity": 64, 
    "type": "context", 
    "name": "101 Dice Ave", 
    "mods": [
      {
        "town_dir": "|", 
        "neighbors": [
          "", 
          "context-region_1067", 
          "", 
          ""
        ], 
        "orientation": 2, 
        "nitty_bits": 3, 
        "port_dir": "|", 
        "type": "Region"
      }
    ]
  }, 
  {
    "ref": "item-Ball_object_1000338", 
    "mods": [
      {
        "style": 0, 
        "orientation": 32, 
        "gr_state": 0, 
        "y": 160, 
        "x": 104, 
        "type": "Ball"
      }
    ], 
    "type": "item", 
    "name": "Ball", 
    "in": "context-region_1068"
  }, 
  {
    "ref": "item-Bag_object_1002865", 
    "mods": [
      {
        "style": 1, 
        "orientation": 0, 
        "key_hi": 0, 
        "key_lo": 0, 
        "gr_state": 0, 
        "y": 134, 
        "x": 138, 
        "type": "Bag", 
        "open_flags": 2
      }
    ], 
    "type": "item", 
    "name": "Bag", 
    "in": "context-region_1068"
  }, 
  {
    "ref": "item-Knife_object_1002861", 
    "mods": [
      {
        "style": 0, 
        "orientation": 16, 
        "gr_state": 0, 
        "y": 1, 
        "x": 148, 
        "type": "Knife"
      }
    ], 
    "type": "item", 
    "name": "Knife", 
    "in": "item-Bag_object_1002865"
  }, 
  {
    "ref": "item-Spray_can_object_1001178", 
    "mods": [
      {
        "style": 0, 
        "orientation": 17, 
        "gr_state": 0, 
        "y": 2, 
        "x": 37, 
        "type": "Spray_can"
      }
    ], 
    "type": "item", 
    "name": "Spray_can", 
    "in": "item-Bag_object_1002865"
  }, 
  {
    "ref": "item-Head_object_1000879", 
    "mods": [
      {
        "style": 24, 
        "orientation": 1, 
        "gr_state": 2, 
        "y": 3, 
        "x": 78, 
        "type": "Head"
      }
    ], 
    "type": "item", 
    "name": "Head", 
    "in": "item-Bag_object_1002865"
  }, 
  {
    "ref": "item-Bag_object_1001165", 
    "mods": [
      {
        "style": 0, 
        "orientation": 48, 
        "key_hi": 0, 
        "key_lo": 0, 
        "gr_state": 0, 
        "y": 0, 
        "x": 121, 
        "type": "Bag", 
        "open_flags": 2
      }
    ], 
    "type": "item", 
    "name": "Bag", 
    "in": "item-Bag_object_1002865"
  }, 
  {
    "ref": "item-Paper_object_1001172", 
    "mods": [
      {
        "style": 0, 
        "orientation": 0, 
        "gr_state": 1, 
        "y": 3, 
        "x": 0, 
        "type": "Paper"
      }
    ], 
    "type": "item", 
    "name": "Paper", 
    "in": "item-Bag_object_1001165"
  }, 
  {
    "ref": "item-Head_object_1002967", 
    "mods": [
      {
        "style": 14, 
        "orientation": 16, 
        "gr_state": 2, 
        "y": 2, 
        "x": 83, 
        "type": "Head"
      }
    ], 
    "type": "item", 
    "name": "Head", 
    "in": "item-Bag_object_1001165"
  }, 
  {
    "ref": "item-Ground_object_2651", 
    "mods": [
      {
        "style": 1, 
        "orientation": 244, 
        "gr_state": 0, 
        "y": 4, 
        "x": 0, 
        "type": "Ground"
      }
    ], 
    "type": "item", 
    "name": "Ground", 
    "in": "context-region_1068"
  }, 
  {
    "ref": "item-Chair_object_2660", 
    "mods": [
      {
        "style": 1, 
        "orientation": 0, 
        "gr_state": 0, 
        "y": 131, 
        "x": 44, 
        "type": "Chair"
      }
    ], 
    "type": "item", 
    "name": "Chair", 
    "in": "context-region_1068"
  }, 
  {
    "ref": "item-Display_case_object_2653", 
    "mods": [
      {
        "style": 0, 
        "orientation": 16, 
        "key_hi": 0, 
        "key_lo": 0, 
        "gr_state": 0, 
        "y": 152, 
        "x": 92, 
        "type": "Display_case", 
        "open_flags": 3
      }
    ], 
    "type": "item", 
    "name": "Display_case", 
    "in": "context-region_1068"
  }, 
  {
    "ref": "item-Knick_knack_object_4774", 
    "mods": [
      {
        "style": 1, 
        "orientation": 1, 
        "gr_state": 0, 
        "y": 0, 
        "x": 9, 
        "type": "Knick_knack", 
        "magic_type": 0
      }
    ], 
    "type": "item", 
    "name": "Knick_knack", 
    "in": "item-Display_case_object_2653"
  }, 
  {
    "ref": "item-Aquarium_object_2656", 
    "mods": [
      {
        "style": 0, 
        "orientation": 0, 
        "gr_state": 1, 
        "y": 2, 
        "x": 70, 
        "type": "Aquarium"
      }
    ], 
    "type": "item", 
    "name": "Aquarium", 
    "in": "item-Display_case_object_2653"
  }, 
  {
    "ref": "item-Wall_object_2652", 
    "mods": [
      {
        "style": 4, 
        "orientation": 180, 
        "gr_state": 0, 
        "y": 0, 
        "x": 0, 
        "type": "Wall"
      }
    ], 
    "type": "item", 
    "name": "Wall", 
    "in": "context-region_1068"
  }, 
  {
    "ref": "item-Door_object_2655", 
    "mods": [
      {
        "style": 0, 
        "orientation": 244, 
        "key_hi": 0, 
        "key_lo": 0, 
        "connection": "context-region_0", 
        "gr_state": 1, 
        "y": 33, 
        "x": 16, 
        "type": "Door", 
        "open_flags": 3
      }
    ], 
    "type": "item", 
    "name": "Door", 
    "in": "context-region_1068"
  }, 
  {
    "ref": "item-Window_object_2654", 
    "mods": [
      {
        "style": 1, 
        "orientation": 8, 
        "gr_state": 2, 
        "y": 104, 
        "x": 20, 
        "type": "Window"
      }
    ], 
    "type": "item", 
    "name": "Window", 
    "in": "context-region_1068"
  }, 
  {
    "ref": "item-Garbage_can_object_2657", 
    "mods": [
      {
        "style": 1, 
        "orientation": 0, 
        "key_hi": 0, 
        "key_lo": 0, 
        "gr_state": 1, 
        "y": 147, 
        "x": 144, 
        "type": "Garbage_can", 
        "open_flags": 3
      }
    ], 
    "type": "item", 
    "name": "Garbage_can", 
    "in": "context-region_1068"
  }, 
  {
    "ref": "item-Chair_object_2659", 
    "mods": [
      {
        "style": 1, 
        "orientation": 1, 
        "gr_state": 0, 
        "y": 130, 
        "x": 96, 
        "type": "Chair"
      }
    ], 
    "type": "item", 
    "name": "Chair", 
    "in": "context-region_1068"
  }, 
  {
    "ref": "item-Window_object_2658", 
    "mods": [
      {
        "style": 1, 
        "orientation": 8, 
        "gr_state": 1, 
        "y": 63, 
        "x": 56, 
        "type": "Window"
      }
    ], 
    "type": "item", 
    "name": "Window", 
    "in": "context-region_1068"
  }, 
  {
    "ref": "item-Knick_knack_object_4804", 
    "mods": [
      {
        "style": 3, 
        "orientation": 24, 
        "gr_state": 0, 
        "y": 160, 
        "x": 104, 
        "type": "Knick_knack", 
        "magic_type": 0
      }
    ], 
    "type": "item", 
    "name": "Knick_knack", 
    "in": "context-region_1068"
  }, 
  {
    "ref": "item-Bag_object_1000285", 
    "mods": [
      {
        "style": 0, 
        "orientation": 64, 
        "key_hi": 0, 
        "key_lo": 0, 
        "gr_state": 0, 
        "y": 160, 
        "x": 104, 
        "type": "Bag", 
        "open_flags": 2
      }
    ], 
    "type": "item", 
    "name": "Bag", 
    "in": "context-region_1068"
  }
]