[
  {
    "ref": "context-region_8075", 
    "capacity": 64, 
    "type": "context", 
    "name": "", 
    "mods": [
      {
        "town_dir": "|", 
        "neighbors": [
          "context-region_8076", 
          "context-region_8074", 
          "context-region_8074", 
          "context-region_8051"
        ], 
        "orientation": 0, 
        "nitty_bits": 3, 
        "port_dir": "|", 
        "type": "Region"
      }
    ]
  }, 
  {
    "ref": "item-Bush_object_5830", 
    "mods": [
      {
        "style": 0, 
        "orientation": 64, 
        "gr_state": 0, 
        "y": 146, 
        "x": 132, 
        "type": "Bush"
      }
    ], 
    "type": "item", 
    "name": "Bush", 
    "in": "context-region_8075"
  }, 
  {
    "ref": "item-Tree_object_5822", 
    "mods": [
      {
        "style": 0, 
        "orientation": 236, 
        "gr_state": 3, 
        "y": 57, 
        "x": 88, 
        "type": "Tree"
      }
    ], 
    "type": "item", 
    "name": "Tree", 
    "in": "context-region_8075"
  }, 
  {
    "ref": "item-Plant_object_5833", 
    "mods": [
      {
        "style": 2, 
        "orientation": 33, 
        "mass": 1, 
        "gr_state": 0, 
        "y": 135, 
        "x": 100, 
        "type": "Plant"
      }
    ], 
    "type": "item", 
    "name": "Plant", 
    "in": "context-region_8075"
  }, 
  {
    "ref": "item-Plant_object_5831", 
    "mods": [
      {
        "style": 2, 
        "orientation": 32, 
        "mass": 1, 
        "gr_state": 0, 
        "y": 148, 
        "x": 4, 
        "type": "Plant"
      }
    ], 
    "type": "item", 
    "name": "Plant", 
    "in": "context-region_8075"
  }, 
  {
    "ref": "item-Plant_object_5832", 
    "mods": [
      {
        "style": 2, 
        "orientation": 32, 
        "mass": 1, 
        "gr_state": 0, 
        "y": 141, 
        "x": 64, 
        "type": "Plant"
      }
    ], 
    "type": "item", 
    "name": "Plant", 
    "in": "context-region_8075"
  }, 
  {
    "ref": "item-Tree_object_5823", 
    "mods": [
      {
        "style": 0, 
        "orientation": 237, 
        "gr_state": 3, 
        "y": 57, 
        "x": 92, 
        "type": "Tree"
      }
    ], 
    "type": "item", 
    "name": "Tree", 
    "in": "context-region_8075"
  }, 
  {
    "ref": "item-Ground_object_5817", 
    "mods": [
      {
        "style": 0, 
        "orientation": 204, 
        "gr_state": 0, 
        "y": 4, 
        "x": 0, 
        "type": "Ground"
      }
    ], 
    "type": "item", 
    "name": "Ground", 
    "in": "context-region_8075"
  }, 
  {
    "ref": "item-Tree_object_5821", 
    "mods": [
      {
        "style": 0, 
        "orientation": 172, 
        "gr_state": 0, 
        "y": 35, 
        "x": 40, 
        "type": "Tree"
      }
    ], 
    "type": "item", 
    "name": "Tree", 
    "in": "context-region_8075"
  }, 
  {
    "ref": "item-Rock_object_5820", 
    "mods": [
      {
        "style": 0, 
        "orientation": 32, 
        "mass": 1, 
        "gr_state": 0, 
        "y": 138, 
        "x": 8, 
        "type": "Rock"
      }
    ], 
    "type": "item", 
    "name": "Rock", 
    "in": "context-region_8075"
  }, 
  {
    "ref": "item-Tree_object_5827", 
    "mods": [
      {
        "style": 0, 
        "orientation": 173, 
        "gr_state": 3, 
        "y": 71, 
        "x": 36, 
        "type": "Tree"
      }
    ], 
    "type": "item", 
    "name": "Tree", 
    "in": "context-region_8075"
  }, 
  {
    "ref": "item-Tree_object_5826", 
    "mods": [
      {
        "style": 0, 
        "orientation": 16, 
        "gr_state": 0, 
        "y": 141, 
        "x": 108, 
        "type": "Tree"
      }
    ], 
    "type": "item", 
    "name": "Tree", 
    "in": "context-region_8075"
  }, 
  {
    "ref": "item-Tree_object_5825", 
    "mods": [
      {
        "style": 0, 
        "orientation": 172, 
        "gr_state": 3, 
        "y": 75, 
        "x": 44, 
        "type": "Tree"
      }
    ], 
    "type": "item", 
    "name": "Tree", 
    "in": "context-region_8075"
  }, 
  {
    "ref": "item-Tree_object_5824", 
    "mods": [
      {
        "style": 0, 
        "orientation": 236, 
        "gr_state": 0, 
        "y": 33, 
        "x": 128, 
        "type": "Tree"
      }
    ], 
    "type": "item", 
    "name": "Tree", 
    "in": "context-region_8075"
  }, 
  {
    "ref": "item-Bush_object_5829", 
    "mods": [
      {
        "style": 0, 
        "orientation": 56, 
        "gr_state": 0, 
        "y": 136, 
        "x": 44, 
        "type": "Bush"
      }
    ], 
    "type": "item", 
    "name": "Bush", 
    "in": "context-region_8075"
  }, 
  {
    "ref": "item-Bush_object_5828", 
    "mods": [
      {
        "style": 0, 
        "orientation": 32, 
        "gr_state": 0, 
        "y": 138, 
        "x": 24, 
        "type": "Bush"
      }
    ], 
    "type": "item", 
    "name": "Bush", 
    "in": "context-region_8075"
  }, 
  {
    "ref": "item-Sky_object_5818", 
    "mods": [
      {
        "style": 4, 
        "orientation": 0, 
        "gr_state": 0, 
        "y": 0, 
        "x": 0, 
        "type": "Sky"
      }
    ], 
    "type": "item", 
    "name": "Sky", 
    "in": "context-region_8075"
  }, 
  {
    "ref": "item-Tree_object_5819", 
    "mods": [
      {
        "style": 0, 
        "orientation": 236, 
        "gr_state": 1, 
        "y": 33, 
        "x": 92, 
        "type": "Tree"
      }
    ], 
    "type": "item", 
    "name": "Tree", 
    "in": "context-region_8075"
  }
]